archer/ArcherAuth.py
archer/ArcherServerClient.py
archer/SigningError.py
archer/__init__.py
uscis_archer-0.0.5.dist-info/METADATA
uscis_archer-0.0.5.dist-info/WHEEL
uscis_archer-0.0.5.dist-info/licenses/LICENSE
uscis_archer-0.0.5.dist-info/RECORD
