Metadata-Version: 2.1
Name: uscis_archer
Version: 0.0.5
Summary: A python module to simplify RSA Archer API calls.
Project-URL: Homepage, https://git.uscis.dhs.gov/jcdavis1/Archer_API
Project-URL: Bug Tracker, https://git.uscis.dhs.gov/jcdavis1/Archer_API/issues
Author-email: Joshua Davis <Joshua.C.Davis@uscis.dhs.gov>
License-File: LICENSE
Classifier: License :: OSI Approved :: MIT License
Classifier: Operating System :: OS Independent
Classifier: Programming Language :: Python :: 3
Requires-Python: >=3.7
